<?xml version='1.0' encoding='utf-8'?>
<mujoco model="porcelain_mug">
  <asset>
  <texture file="porcelain_mug_texture.png" name="tex-porcelain_mug" type="2d" />
  <material name="porcelain_mug" reflectance="0.5" texrepeat="1 1" texture="tex-porcelain_mug" texuniform="false" />
  <mesh file="visual/porcelain_mug_vis.msh" name="porcelain_mug_vis" scale="0.6 0.6 0.6" /></asset>
  <worldbody>
    <body>
      <body name="object">
      <geom solimp="0.998 0.998 0.001" solref="0.001 1" density="100" friction="0.95 0.3 0.1" type="mesh" mesh="porcelain_mug_vis" conaffinity="0" contype="0" group="1" material="porcelain_mug" /><geom solimp="0.998 0.998 0.001" solref="0.001 1" density="100" friction="0.95 0.3 0.1" type="box" pos="-0.035718 -0.0 0.033611999999999996" quat="0.00000 0.00000 1.00000 0.00000" size="0.0022559999999999998 0.004782 0.01185" group="0" rgba="0.8 0.8 0.8 0.3" /><geom solimp="0.998 0.998 0.001" solref="0.001 1" density="100" friction="0.95 0.3 0.1" type="box" pos="-0.024947999999999998 0.0 0.017172" quat="0.50997 -0.00000 0.86019 -0.00000" size="0.0022559999999999998 0.004782 0.01185" group="0" rgba="0.8 0.8 0.8 0.3" /><geom solimp="0.998 0.998 0.001" solref="0.001 1" density="100" friction="0.95 0.3 0.1" type="box" pos="-0.02778 -0.0 0.05005199999999999" quat="0.46390 0.00000 -0.88589 0.00000" size="0.0022559999999999998 0.004782 0.01185" group="0" rgba="0.8 0.8 0.8 0.3" /><geom solimp="0.998 0.998 0.001" solref="0.001 1" density="100" friction="0.95 0.3 0.1" type="box" pos="0.034067999999999994 -0.000882 0.04551" quat="0.00000 0.00000 1.00000 0.00000" size="0.0014579999999999999 0.012978 0.019566" group="0" rgba="0.8 0.8 0.8 0.3" /><geom solimp="0.998 0.998 0.001" solref="0.001 1" density="100" friction="0.95 0.3 0.1" type="box" pos="0.008862 -0.0009839999999999998 0.00456" quat="0.50000 -0.50000 0.50000 0.50000" size="0.003126 0.011159999999999998 0.011159999999999998" group="0" rgba="0.8 0.8 0.8 0.3" /><geom solimp="0.998 0.998 0.001" solref="0.001 1" density="100" friction="0.95 0.3 0.1" type="box" pos="0.029609999999999997 -0.0024179999999999996 0.01434" quat="0.69215 0.69215 0.14468 -0.14468" size="0.000846 0.011334 0.012978" group="0" rgba="0.8 0.8 0.8 0.3" /><geom solimp="0.998 0.998 0.001" solref="0.001 1" density="100" friction="0.95 0.3 0.1" type="box" pos="0.023472 0.014664 0.01434" quat="0.68797 0.56492 0.42528 0.16339" size="0.000792 0.011196 0.011453999999999999" group="0" rgba="0.8 0.8 0.8 0.3" /><geom solimp="0.998 0.998 0.001" solref="0.001 1" density="100" friction="0.95 0.3 0.1" type="box" pos="0.024516 0.018708 0.04551" quat="0.00000 -0.42525 0.90508 0.00000" size="0.0014579999999999999 0.012978 0.019566" group="0" rgba="0.8 0.8 0.8 0.3" /><geom solimp="0.998 0.998 0.001" solref="0.001 1" density="100" friction="0.95 0.3 0.1" type="box" pos="0.005267999999999999 0.023208 0.04551" quat="0.00000 -0.76965 0.63846 0.00000" size="0.0014579999999999999 0.012978 0.019566" group="0" rgba="0.8 0.8 0.8 0.3" /><geom solimp="0.998 0.998 0.001" solref="0.001 1" density="100" friction="0.95 0.3 0.1" type="box" pos="0.0064139999999999996 0.017202 0.01434" quat="0.55326 0.33057 0.62508 0.44034" size="0.000846 0.011334 0.012978" group="0" rgba="0.8 0.8 0.8 0.3" /><geom solimp="0.998 0.998 0.001" solref="0.001 1" density="100" friction="0.95 0.3 0.1" type="box" pos="-0.006834000000000001 0.007632 0.01434" quat="0.01588 -0.29770 -0.64138 0.70693" size="0.000846 0.011334 0.012978" group="0" rgba="0.8 0.8 0.8 0.3" /><geom solimp="0.998 0.998 0.001" solref="0.001 1" density="100" friction="0.95 0.3 0.1" type="box" pos="-0.013151999999999999 0.010722 0.04551" quat="0.00000 -0.97400 0.22653 0.00000" size="0.0014579999999999999 0.012978 0.019566" group="0" rgba="0.8 0.8 0.8 0.3" /><geom solimp="0.998 0.998 0.001" solref="0.001 1" density="100" friction="0.95 0.3 0.1" type="box" pos="-0.013722 -0.010824 0.04551" quat="0.00000 -0.23315 0.97244 0.00000" size="0.0014639999999999998 0.012978 0.019566" group="0" rgba="0.8 0.8 0.8 0.3" /><geom solimp="0.998 0.998 0.001" solref="0.001 1" density="100" friction="0.95 0.3 0.1" type="box" pos="-0.010493999999999998 -0.00825 0.01434" quat="0.02182 -0.26310 0.65634 0.70677" size="0.0008399999999999999 0.011315999999999998 0.011951999999999999" group="0" rgba="0.8 0.8 0.8 0.3" /><geom solimp="0.998 0.998 0.001" solref="0.001 1" density="100" friction="0.95 0.3 0.1" type="box" pos="0.0049559999999999995 -0.020987999999999996 0.01434" quat="0.52881 -0.29653 0.64193 -0.46942" size="0.000846 0.011328 0.012414" group="0" rgba="0.8 0.8 0.8 0.3" /><geom solimp="0.998 0.998 0.001" solref="0.001 1" density="100" friction="0.95 0.3 0.1" type="box" pos="0.0038759999999999997 -0.023964000000000003 0.04551" quat="-0.00000 -0.76567 -0.64323 -0.00000" size="0.0014579999999999999 0.012978 0.019566" group="0" rgba="0.8 0.8 0.8 0.3" /><geom solimp="0.998 0.998 0.001" solref="0.001 1" density="100" friction="0.95 0.3 0.1" type="box" pos="0.025032 -0.019482 0.04551" quat="0.00000 0.41049 0.91187 0.00000" size="0.0014579999999999999 0.012978 0.019566" group="0" rgba="0.8 0.8 0.8 0.3" /><geom solimp="0.998 0.998 0.001" solref="0.001 1" density="100" friction="0.95 0.3 0.1" type="box" pos="0.02274 -0.015486 0.01434" quat="0.69053 -0.57176 0.41604 -0.15219" size="0.000846 0.011334 0.012978" group="0" rgba="0.8 0.8 0.8 0.3" /><geom solimp="0.998 0.998 0.001" solref="0.001 1" density="100" friction="0.95 0.3 0.1" type="box" pos="0.009174 -0.014346 0.00456" quat="0.50000 0.50000 -0.50000 -0.50000" size="0.001956 0.003126 0.009323999999999999" group="0" rgba="0.8 0.8 0.8 0.3" /><geom solimp="0.998 0.998 0.001" solref="0.001 1" density="100" friction="0.95 0.3 0.1" type="box" pos="0.022494 -0.000102 0.00456" quat="0.70711 0.70711 0.00000 -0.00000" size="0.00216 0.003126 0.009858" group="0" rgba="0.8 0.8 0.8 0.3" /><geom solimp="0.998 0.998 0.001" solref="0.001 1" density="100" friction="0.95 0.3 0.1" type="box" pos="-0.0031439999999999997 -0.002526 0.00456" quat="0.70711 0.70711 0.00000 -0.00000" size="0.00216 0.003126 0.009858" group="0" rgba="0.8 0.8 0.8 0.3" /><geom solimp="0.998 0.998 0.001" solref="0.001 1" density="100" friction="0.95 0.3 0.1" type="box" pos="0.009174 0.011322 0.00456" quat="0.50000 0.50000 -0.50000 -0.50000" size="0.001956 0.003126 0.009323999999999999" group="0" rgba="0.8 0.8 0.8 0.3" /></body>
      <site rgba="0 0 0 0" size="0.003" pos="0.0 0.0 -0.036" name="bottom_site" />
      <site rgba="0 0 0 0" size="0.003" pos="0.0 0.0 0.024" name="top_site" />
      <site rgba="0 0 0 0" size="0.003" pos="0.015 0.015 0.0" name="horizontal_radius_site" />
    </body>
  </worldbody>
</mujoco>